PyNormaliz.py
PyNormaliz_cpp.cpython-314t-i386-linux-musl.so
pynormaliz.libs/libeantic-8a3371f3.so.3.1.0
pynormaliz.libs/libeanticxx-47fc468c.so.3.1.0
pynormaliz.libs/libflint-023523f3.so.21.0.0
pynormaliz.libs/libgcc_s-e1925712.so.1
pynormaliz.libs/libgmp-711471aa.so.10.5.0
pynormaliz.libs/libgmpxx-99440298.so.4.7.0
pynormaliz.libs/libgomp-6d7f45f1.so.1.0.0
pynormaliz.libs/libmpfr-d65b6c29.so.6.2.1
pynormaliz.libs/libnormaliz-8d13ad29.so.3.11.0
pynormaliz.libs/libstdc++-b2d5af4b.so.6.0.33
pynormaliz-2.23.dist-info/METADATA
pynormaliz-2.23.dist-info/WHEEL
pynormaliz-2.23.dist-info/top_level.txt
pynormaliz-2.23.dist-info/RECORD
pynormaliz-2.23.dist-info/licenses/COPYING
