Metadata-Version: 2.4
Name: PyNormaliz
Version: 2.23
Summary: An interface to Normaliz
Home-page: https://github.com/Normaliz/PyNormaliz
Author: Sebastian Gutsche, Richard Sieg, Winfried Bruns
Author-email: wbruns@uos.de
License-File: COPYING
Dynamic: license-file
